tempmailchecker/__init__.py
tempmailchecker/client.py
tempmailchecker-1.0.0.dist-info/licenses/LICENSE
tempmailchecker-1.0.0.dist-info/METADATA
tempmailchecker-1.0.0.dist-info/WHEEL
tempmailchecker-1.0.0.dist-info/top_level.txt
tempmailchecker-1.0.0.dist-info/RECORD
