Metadata-Version: 2.4
Name: tempmailchecker
Version: 1.0.0
Summary: Python SDK for TempMailChecker API - Detect disposable email addresses in real-time
Author-email: TempMailChecker <support@tempmailchecker.com>
License: MIT
Project-URL: Homepage, https://github.com/Fushey/python-disposable-email-checker
Project-URL: Documentation, https://tempmailchecker.com/docs
Project-URL: Repository, https://github.com/Fushey/python-disposable-email-checker
Project-URL: Issues, https://github.com/Fushey/python-disposable-email-checker/issues
Keywords: email,disposable,temporary,validation,tempmail,spam,api,sdk,python
Classifier: Development Status :: 4 - Beta
Classifier: Intended Audience :: Developers
Classifier: License :: OSI Approved :: MIT License
Classifier: Programming Language :: Python :: 3
Classifier: Programming Language :: Python :: 3.7
Classifier: Programming Language :: Python :: 3.8
Classifier: Programming Language :: Python :: 3.9
Classifier: Programming Language :: Python :: 3.10
Classifier: Programming Language :: Python :: 3.11
Classifier: Programming Language :: Python :: 3.12
Classifier: Topic :: Software Development :: Libraries :: Python Modules
Classifier: Topic :: Communications :: Email
Requires-Python: >=3.7
License-File: LICENSE
Requires-Dist: requests>=2.25.0
Dynamic: license-file
Dynamic: requires-python
